{"frameRate":24,"armature":[{"defaultActions":[{"gotoAndPlay":"idle"}],"type":"Armature","frameRate":24,"ik":[],"skin":[{"slot":[{"display":[{"path":"bullet_01_f/bullet_01","type":"image","name":"bullet_01_f/bullet_01","transform":{"x":-27}}],"name":"b"}],"name":""}],"aabb":{"width":74,"y":-10,"height":20,"x":-64},"animation":[{"frame":[],"slot":[{"displayFrame":[],"colorFrame":[{"duration":2,"color":{"aM":0},"tweenEasing":0},{"duration":8,"color":{"aM":50},"tweenEasing":0},{"duration":2,"color":{"aM":50},"tweenEasing":0},{"duration":0,"color":{"aM":0}}],"name":"b"}],"duration":12,"name":"idle","bone":[{"rotateFrame":[],"translateFrame":[],"scaleFrame":[],"name":"root"},{"rotateFrame":[],"translateFrame":[{"tweenEasing":0,"duration":12},{"x":100,"duration":0}],"scaleFrame":[{"x":0.1,"y":0.3,"tweenEasing":0,"duration":4},{"x":1.8,"y":1.1,"duration":8}],"name":"bullet"}],"ffd":[]}],"slot":[{"color":{"aM":50},"name":"b","parent":"bullet"}],"name":"bullet_01","bone":[{"length":20,"name":"root","transform":{}},{"length":20,"transform":{},"parent":"root","inheritScale":false,"name":"bullet"}]}],"name":"bullet_01","version":"5.5","isGlobal":0}